KMeansImage/Display.py
KMeansImage/Interactive.py
KMeansImage/Preprocessing.py
KMeansImage/Save.py
KMeansImage/__init__.py
KMeansImage/kmeans.py
KMeansImage-1.0.dist-info/LICENSE
KMeansImage-1.0.dist-info/METADATA
KMeansImage-1.0.dist-info/WHEEL
KMeansImage-1.0.dist-info/top_level.txt
KMeansImage-1.0.dist-info/RECORD
