Metadata-Version: 2.1
Name: KMeansImage
Version: 1.0
Summary: A K-Means based image compressor. Consists interactive widgets for Jupyter Notebook
Home-page: https://github.com/imsahil007/KMeansImage
Author: Sahil
Author-email: sahils.1997.s@gmail.com
License: UNKNOWN
Download-URL: https://github.com/imsahil007/KMeansImage/blob/master/dist/KMeansImage-0.69.tar.gz
Platform: UNKNOWN
Classifier: Programming Language :: Python :: 3
Classifier: License :: OSI Approved :: MIT License
Classifier: Operating System :: OS Independent
Requires-Python: >=3.0
Requires-Dist: scikit-image
Requires-Dist: ipywidgets
Requires-Dist: matplotlib
Requires-Dist: scikit-learn
Requires-Dist: numpy
